allrank/__init__.py
allrank/config.py
allrank/main.py
allrank/rank_and_click.py
allrank/click_models/__init__.py
allrank/click_models/base.py
allrank/click_models/cascade_models.py
allrank/click_models/click_utils.py
allrank/click_models/duplicate_aware.py
allrank/data/__init__.py
allrank/data/dataset_loading.py
allrank/data/dataset_saving.py
allrank/data/generate_dummy_data.py
allrank/inference/__init__.py
allrank/inference/inference_utils.py
allrank/models/__init__.py
allrank/models/metrics.py
allrank/models/model.py
allrank/models/model_utils.py
allrank/models/positional.py
allrank/models/transformer.py
allrank/models/losses/__init__.py
allrank/models/losses/approxNDCG.py
allrank/models/losses/bce.py
allrank/models/losses/binary_listNet.py
allrank/models/losses/lambdaLoss.py
allrank/models/losses/listMLE.py
allrank/models/losses/listNet.py
allrank/models/losses/loss_utils.py
allrank/models/losses/neuralNDCG.py
allrank/models/losses/ordinal.py
allrank/models/losses/pointwise.py
allrank/models/losses/rankNet.py
allrank/training/__init__.py
allrank/training/early_stop.py
allrank/training/train_utils.py
allrank/utils/__init__.py
allrank/utils/args_utils.py
allrank/utils/command_executor.py
allrank/utils/config_utils.py
allrank/utils/experiments.py
allrank/utils/file_utils.py
allrank/utils/ltr_logging.py
allrank/utils/python_utils.py
allrank/utils/tensorboard_utils.py
tests/click_models/__init__.py
tests/click_models/test_alternative_click_models.py
tests/click_models/test_apply_click_model.py
tests/click_models/test_base_cascade_model.py
tests/click_models/test_diverse_clicks_model.py
tests/click_models/test_duplicate_click_model.py
tests/click_models/test_feature_click_model.py
tests/click_models/test_fixed_click_model.py
tests/click_models/test_masked_click_model.py
tests/click_models/test_random_click_model.py
tests/losses/__init__.py
tests/losses/test_approxndcg.py
tests/losses/test_binary_listnet.py
tests/losses/test_lambdaloss.py
tests/losses/test_listmle.py
allRank-1.4.3.dist-info/LICENSE
allRank-1.4.3.dist-info/METADATA
allRank-1.4.3.dist-info/WHEEL
allRank-1.4.3.dist-info/entry_points.txt
allRank-1.4.3.dist-info/top_level.txt
allRank-1.4.3.dist-info/RECORD
