Metadata-Version: 2.1
Name: allRank
Version: 1.4.3
Summary: allRank is a framework for training learning-to-rank neural models
Home-page: https://github.com/allegro/allRank
Author-email: allrank@allegro.pl
License: Apache 2
Platform: UNKNOWN
Requires-Dist: torch (<=1.8.0,>=1.6.0)
Requires-Dist: torchvision (<=0.9.0,>=0.7.0)
Requires-Dist: scikit-learn (>=0.23.0)
Requires-Dist: pandas (>=1.0.5)
Requires-Dist: numpy (>=1.18.5)
Requires-Dist: scipy (>=1.4.1)
Requires-Dist: attrs (>=19.3.0)
Requires-Dist: flatten-dict (>=0.3.0)
Requires-Dist: tensorboardX (>=2.1.0)
Requires-Dist: gcsfs (==0.6.2)
Requires-Dist: google-auth (==1.27.1)
